Tool.py
setup.py
sualgoodzhao/__init__.py
sualgoodzhao/testone.py
sualgoodzhao.egg-info/PKG-INFO
sualgoodzhao.egg-info/SOURCES.txt
sualgoodzhao.egg-info/dependency_links.txt
sualgoodzhao.egg-info/top_level.txt