Metadata-Version: 2.1
Name: sualgoodzhao
Version: 1.0.0
Summary: this is a very amaziong package
Author: qingquanzhao
Author-email: 1259567750@qq.com
License: UNKNOWN
Platform: UNKNOWN
